AUTHORS
LICENSE
MANIFEST.in
README.rst
requirements.txt
setup.py
test-requirements.txt
tox.ini
Fiblary.egg-info/SOURCES.txt
docs/Makefile
docs/source/conf.py
docs/source/index.rst
docs/source/make.bat
fiblary/__init__.py
fiblary.egg-info/PKG-INFO
fiblary.egg-info/SOURCES.txt
fiblary.egg-info/dependency_links.txt
fiblary.egg-info/not-zip-safe
fiblary.egg-info/requires.txt
fiblary.egg-info/top_level.txt
fiblary/client/__init__.py
fiblary/client/v3/__init__.py
fiblary/client/v3/base.py
fiblary/client/v3/client.py
fiblary/client/v3/devices.py
fiblary/client/v3/events.py
fiblary/client/v3/info.py
fiblary/client/v3/login.py
fiblary/client/v3/models.py
fiblary/client/v3/rooms.py
fiblary/client/v3/scenes.py
fiblary/client/v3/sections.py
fiblary/client/v3/users.py
fiblary/client/v3/variables.py
fiblary/client/v3/weather.py
fiblary/common/__init__.py
fiblary/common/beacon.py
fiblary/common/event.py
fiblary/common/exceptions.py
fiblary/common/net.py
fiblary/common/restapi.py
fiblary/common/timestamp.py
fiblary/common/utils.py
fiblary/external/__init__.py
fiblary/external/jsonpath.py
fiblary/tests/__init__.py
fiblary/tests/utils.py
fiblary/tests/unit/__init__.py
fiblary/tests/unit/test_event.py
fiblary/tests/unit/test_restapi.py
fiblary/tests/unit/test_timestamp.py
fiblary/tests/unit/test_utils.py