Metadata-Version: 1.1
Name: fiblary
Version: 0.1.3
Summary: Home Center 2 API Python Library
Home-page: https://github.com/kstaniek/fiblary
Author: Klaudiusz Staniek
Author-email: klaudiusz@staniek.name
License: Apache 2.0
Platform: UNKNOWN
Classifier: Development Status :: 5 - Production/Stable
Classifier: Intended Audience :: Developers
Classifier: Natural Language :: English
Classifier: License :: OSI Approved :: Apache Software License
Classifier: Operating System :: POSIX :: Linux
Classifier: Programming Language :: Python
Classifier: Programming Language :: Python :: 2.7
